strands_telegram/__init__.py
strands_telegram/telegram.py
strands_telegram-1.0.2.dist-info/licenses/LICENSE
strands_telegram-1.0.2.dist-info/METADATA
strands_telegram-1.0.2.dist-info/WHEEL
strands_telegram-1.0.2.dist-info/top_level.txt
strands_telegram-1.0.2.dist-info/RECORD
