Metadata-Version: 2.4
Name: strands-telegram
Version: 1.0.2
Summary: Comprehensive Telegram Bot API integration for Strands Agents
Author-email: Strands Community <community@strandsagents.com>
License: MIT
Project-URL: Homepage, https://github.com/eraykeskinmac/strands-telegram
Project-URL: Documentation, https://github.com/eraykeskinmac/strands-telegram#readme
Project-URL: Repository, https://github.com/eraykeskinmac/strands-telegram.git
Project-URL: Bug Tracker, https://github.com/eraykeskinmac/strands-telegram/issues
Project-URL: Changelog, https://github.com/eraykeskinmac/strands-telegram/blob/main/CHANGELOG.md
Keywords: strands,agents,telegram,bot,api,ai,chatbot,messaging,automation,integration
Classifier: Development Status :: 5 - Production/Stable
Classifier: Intended Audience :: Developers
Classifier: License :: OSI Approved :: MIT License
Classifier: Operating System :: OS Independent
Classifier: Programming Language :: Python :: 3.10
Classifier: Programming Language :: Python :: 3.11
Classifier: Programming Language :: Python :: 3.12
Classifier: Programming Language :: Python :: 3.13
Classifier: Topic :: Communications :: Chat
Classifier: Topic :: Internet :: WWW/HTTP :: Dynamic Content
Classifier: Topic :: Software Development :: Libraries :: Python Modules
Classifier: Topic :: Scientific/Engineering :: Artificial Intelligence
Requires-Python: >=3.10
License-File: LICENSE
Requires-Dist: strands-agents>=1.0.0
Requires-Dist: requests>=2.25.0
Provides-Extra: dev
Requires-Dist: pytest>=7.0.0; extra == "dev"
Requires-Dist: pytest-cov>=4.0.0; extra == "dev"
Requires-Dist: pytest-asyncio>=0.20.0; extra == "dev"
Requires-Dist: black>=22.0.0; extra == "dev"
Requires-Dist: isort>=5.10.0; extra == "dev"
Requires-Dist: flake8>=5.0.0; extra == "dev"
Requires-Dist: mypy>=1.0.0; extra == "dev"
Requires-Dist: pre-commit>=2.17.0; extra == "dev"
Provides-Extra: test
Requires-Dist: pytest>=7.0.0; extra == "test"
Requires-Dist: pytest-cov>=4.0.0; extra == "test"
Requires-Dist: pytest-asyncio>=0.20.0; extra == "test"
Requires-Dist: responses>=0.23.0; extra == "test"
Requires-Dist: pytest-mock>=3.10.0; extra == "test"
Dynamic: license-file
